{
  "name": "AirRohr",
  "accessory": "airrohr",
  "json_data": "http://feinstaubsensor-2342523.local/data.json",
  "public_temperature_json_data": "http://data.sensor.community/airrohr/v1/sensor/18499/",
  "public_airquality_json_data": "http://data.sensor.community/airrohr/v1/sensor/2342/",
  "sensor_id": "2342523",
  "update_interval_seconds": 60,
  "history": {
    "storage": "fs"
  },
  "disable_humidity": false,
  "disable_temperature": false,
  "disable_pressure": false,
  "disable_pm25": false,
  "disable_pm10": false,
  "daily_limits": {
    "pm10": 50.0,
    "pm25": 25.0
  }
}
